ndslice/__init__.py
ndslice/__main__.py
ndslice/file_interpreters.py
ndslice/imageview2d.py
ndslice/ndslice.py
ndslice/selectors.py
ndslice/video_export.py
ndslice-0.4.1.dist-info/licenses/LICENSE
ndslice-0.4.1.dist-info/METADATA
ndslice-0.4.1.dist-info/WHEEL
ndslice-0.4.1.dist-info/entry_points.txt
ndslice-0.4.1.dist-info/top_level.txt
ndslice-0.4.1.dist-info/RECORD
