Metadata-Version: 2.4
Name: ndslice
Version: 0.4.1
Summary: Interactive N-dimensional numpy array viewer with FFT support
Author-email: Henric Rydén <henric.ryden@gmail.com>
License: MIT
Project-URL: Homepage, https://github.com/henricryden/ndslice
Project-URL: Documentation, https://github.com/henricryden/ndslice#readme
Project-URL: Repository, https://github.com/henricryden/ndslice
Project-URL: Bug Tracker, https://github.com/henricryden/ndslice/issues
Keywords: visualization,numpy,fft,image-viewer,data-visualization
Classifier: Development Status :: 4 - Beta
Classifier: Intended Audience :: Developers
Classifier: Intended Audience :: Science/Research
Classifier: License :: OSI Approved :: MIT License
Classifier: Programming Language :: Python :: 3
Classifier: Programming Language :: Python :: 3.8
Classifier: Programming Language :: Python :: 3.9
Classifier: Programming Language :: Python :: 3.10
Classifier: Programming Language :: Python :: 3.11
Classifier: Programming Language :: Python :: 3.12
Classifier: Topic :: Scientific/Engineering :: Visualization
Requires-Python: >=3.8
License-File: LICENSE
Requires-Dist: numpy>=1.20.0
Requires-Dist: pyqtgraph>=0.12.0
Requires-Dist: PyQt5>=5.15.0
Provides-Extra: dev
Requires-Dist: build>=0.10.0; extra == "dev"
Requires-Dist: twine>=4.0.0; extra == "dev"
Provides-Extra: hdf5
Requires-Dist: h5py>=3.0.0; extra == "hdf5"
Provides-Extra: matlab
Requires-Dist: scipy>=1.7.0; extra == "matlab"
Provides-Extra: all
Requires-Dist: h5py>=3.0.0; extra == "all"
Requires-Dist: scipy>=1.7.0; extra == "all"
Provides-Extra: dicom
Requires-Dist: pydicom>=2.4.0; extra == "dicom"
Provides-Extra: nifti
Requires-Dist: nibabel>=4.0.0; extra == "nifti"
Provides-Extra: video-export
Requires-Dist: imageio>=2.9.0; extra == "video-export"
Requires-Dist: imageio-ffmpeg>=0.4.2; extra == "video-export"
Requires-Dist: Pillow>=8.0.0; extra == "video-export"
Dynamic: license-file
